adder.v
// Adder circuit

`define AND and #50
`define OR or #50
`define XOR xor #50
`define NOT not #50

module behavioralFullAdder
(
    output sum, 
    output carryout,
    input a, 
    input b, 
    input carryin
);
    // Uses concatenation operator and built-in '+'
    assign {carryout, sum}=a+b+carryin;
endmodule

module structuralFullAdder
(
    output sum, 
    output carryout,
    input a, 
    input b, 
    input carryin
);
    wire andab, andbIn, andaIn;
    wire orab, orbIn;
    wire orOut;

    `AND andAB(andab, a, b);
    `AND andBIN(andbIn, b, carryin);
    `AND andAIN(andaIn, a, carryin);

    `OR or1(orOut, andab, andbIn);
    `OR or2(carryout, orOut, andaIn);


    `XOR xor1(orab, a, b);
    `XOR xor2(sum, orab, carryin); 
endmodule

adder.t.v
// Adder testbench
`timescale 1 ns / 1 ps
`include "adder.v"

module testFullAdder();
    reg a, b, carryin;
    wire sum, carryout;

    //behavioralFullAdder adder (sum, carryout, a, b, carryin);
    structuralFullAdder adder (sum, carryout, a, b, carryin);

    initial begin

    	$dumpfile("adder.vcd");
    	$dumpvars(0,adder);

        $display(" A B | Cin | Cout | Sum | ExCout | ExSum");
        a=0;b=0;carryin=0; #1000
        $display(" %b %b |  %b  |  %b   |  %b  |   0    |   0", a, b, carryin, carryout, sum);
        a=0;b=0;carryin=1; #1000
        $display(" %b %b |  %b  |  %b   |  %b  |   0    |   1", a, b, carryin, carryout, sum);
        a=0;b=1;carryin=0; #1000
        $display(" %b %b |  %b  |  %b   |  %b  |   0    |   1", a, b, carryin, carryout, sum);
        a=0;b=1;carryin=1; #1000
        $display(" %b %b |  %b  |  %b   |  %b  |   1    |   0", a, b, carryin, carryout, sum);
        a=1;b=0;carryin=0; #1000
        $display(" %b %b |  %b  |  %b   |  %b  |   0    |   1", a, b, carryin, carryout, sum);
        a=1;b=0;carryin=1; #1000
        $display(" %b %b |  %b  |  %b   |  %b  |   1    |   0", a, b, carryin, carryout, sum);
        a=1;b=1;carryin=0; #1000
        $display(" %b %b |  %b  |  %b   |  %b  |   1    |   0", a, b, carryin, carryout, sum);
        a=1;b=1;carryin=1; #1000
        $display(" %b %b |  %b  |  %b   |  %b  |   1    |   1", a, b, carryin, carryout, sum);
    end
endmodule

Progress Files/adder.vcd
$date
	Sun Sep 16 14:39:33 2018
$end
$version
	Icarus Verilog
$end
$timescale
	1ps
$end
$scope module testFullAdder $end
$scope module adder $end
$var wire 1 ! a $end
$var wire 1 " andaIn $end
$var wire 1 # andab $end
$var wire 1 $ andbIn $end
$var wire 1 % b $end
$var wire 1 & carryin $end
$var wire 1 ' carryout $end
$var wire 1 ( orOut $end
$var wire 1 ) orab $end
$var wire 1 * sum $end
$upscope $end
$upscope $end
$enddefinitions $end
#0
$dumpvars
x*
x)
x(
x'
0&
0%
x$
x#
x"
0!
$end
#50000
0)
0"
0$
0#
#100000
0*
0(
#150000
0'
#1000000
1&
#1050000
1*
#2000000
0&
1%
#2050000
0*
1)
#2100000
1*
#3000000
1&
#3050000
1$
0*
#3100000
1(
#3150000
1'
#4000000
0&
0%
1!
#4050000
1*
0$
#4100000
0(
#4150000
0'
#5000000
1&
#5050000
1"
0*
#5100000
1'
#6000000
0&
1%
#6050000
0"
1*
1#
0)
#6100000
0'
1(
0*
#6150000
1'
#7000000
1&
#7050000
1$
1"
1*
