multiplexer.v
// Multiplexer circuit

`define AND and #50
`define OR or #50
`define NOT not #50

module behavioralMultiplexer
(
    output out,
    input address0, address1,
    input in0, in1, in2, in3
);
    // Join single-bit inputs into a bus, use address as index
    wire[3:0] inputs = {in3, in2, in1, in0};
    wire[1:0] address = {address1, address0};
    assign out = inputs[address];
endmodule


module structuralMultiplexer
(
    output out,
    input address0, address1,
    input in0, in1, in2, in3
);

    wire add0inv, add1inv;
    wire is0, is1, is2, is3;
    wire out0, out1, out2, out3;
    wire out01, out23;

    `NOT not0(add0inv, address0);
    `NOT not1(add1inv, address1);

    `AND and0(is0, add0inv, add1inv);
    `AND and1(is1, address0, add1inv);
    `AND and2(is2, add0inv, address1);
    `AND and3(is3, address0, address1);

    `AND and0sig(out0, is0, in0);
    `AND and1sig(out1, is1, in1);
    `AND and2sig(out2, is2, in2);
    `AND and3sig(out3, is3, in3);

    `OR or01(out01, out0, out1);
    `OR or23(out23, out2, out3);

    `OR orOut(out, out01, out23);
    
endmodule

multiplexer.t.v
// Multiplexer testbench
`timescale 1 ns / 1 ps
`include "multiplexer.v"

module testMultiplexer ();
  	reg addr0, addr1;
    reg in0, in1, in2, in3;
    wire out;

    // behavioralMultiplexer multiplexer (out, addr0, addr1, in0, in1, in2, in3);
    structuralMultiplexer multiplexer (out, addr0, addr1, in0, in1, in2, in3); // Swap after testing

    initial begin

    $dumpfile("multiplexer.vcd");
    $dumpvars(0, multiplexer);

    $display("A0 A1 | in0 in1 in2 in3 | EX_OUT | Out");
    addr0=0;addr1=0;in0=1;in1=0;in2=0;in3=0; #1000 
    $display(" %b  %b |  %b   %b   %b   %b  |    %b   |  %b", addr1, addr0, in0, in1, in2, in3, in0, out);
    addr0=1;addr1=0;in0=0;in1=1;in2=0;in3=0; #1000 
    $display(" %b  %b |  %b   %b   %b   %b  |    %b   |  %b", addr1, addr0, in0, in1, in2, in3, in1, out);
    addr0=0;addr1=1;in0=0;in1=0;in2=1;in3=0; #1000  
    $display(" %b  %b |  %b   %b   %b   %b  |    %b   |  %b", addr1, addr0, in0, in1, in2, in3, in2, out);
    addr0=1;addr1=1;in0=0;in1=0;in2=0;in3=1; #1000 
    $display(" %b  %b |  %b   %b   %b   %b  |    %b   |  %b", addr1, addr0, in0, in1, in2, in3, in3, out);
    addr0=0;addr1=0;in0=0;in1=1;in2=1;in3=1; #1000  
    $display(" %b  %b |  %b   %b   %b   %b  |    %b   |  %b", addr1, addr0, in0, in1, in2, in3, in0, out);
    addr0=1;addr1=0;in0=1;in1=0;in2=1;in3=1; #1000
    $display(" %b  %b |  %b   %b   %b   %b  |    %b   |  %b", addr1, addr0, in0, in1, in2, in3, in1, out);
    addr0=0;addr1=1;in0=1;in1=1;in2=0;in3=1; #1000
    $display(" %b  %b |  %b   %b   %b   %b  |    %b   |  %b", addr1, addr0, in0, in1, in2, in3, in2, out);
    addr0=1;addr1=1;in0=1;in1=1;in2=1;in3=0; #1000
    $display(" %b  %b |  %b   %b   %b   %b  |    %b   |  %b", addr1, addr0, in0, in1, in2, in3, in3, out);
    end
endmodule

Progress Files/multiplexer.vcd
$date
	Sun Sep 16 14:39:43 2018
$end
$version
	Icarus Verilog
$end
$timescale
	1ps
$end
$scope module testMultiplexer $end
$scope module multiplexer $end
$var wire 1 ! add0inv $end
$var wire 1 " add1inv $end
$var wire 1 # address0 $end
$var wire 1 $ address1 $end
$var wire 1 % in0 $end
$var wire 1 & in1 $end
$var wire 1 ' in2 $end
$var wire 1 ( in3 $end
$var wire 1 ) is0 $end
$var wire 1 * is1 $end
$var wire 1 + is2 $end
$var wire 1 , is3 $end
$var wire 1 - out $end
$var wire 1 . out0 $end
$var wire 1 / out01 $end
$var wire 1 0 out1 $end
$var wire 1 1 out2 $end
$var wire 1 2 out23 $end
$var wire 1 3 out3 $end
$upscope $end
$upscope $end
$enddefinitions $end
#0
$dumpvars
x3
x2
x1
x0
x/
x.
x-
x,
x+
x*
x)
0(
0'
0&
1%
0$
0#
x"
x!
$end
#50000
1"
1!
03
01
00
0,
0+
0*
#100000
1)
02
#150000
1.
#200000
1/
#250000
1-
#1000000
1&
0%
1#
#1050000
0.
0!
1*
#1100000
0/
0)
10
#1150000
0-
1/
#1200000
1-
#2000000
1'
0&
1$
0#
#2050000
00
0"
1!
0*
#2100000
0/
1+
#2150000
0-
11
#2200000
12
#2250000
1-
#3000000
1(
0'
1#
#3050000
01
0!
1,
#3100000
02
0+
13
#3150000
0-
12
#3200000
1-
#4000000
1'
1&
0$
0#
#4050000
1"
1!
0,
#4100000
1)
03
#4150000
02
#4200000
0-
#5000000
0&
1%
1#
#5050000
1.
0!
1*
#5100000
1/
0)
#5150000
1-
0.
#5200000
0/
#5250000
0-
#6000000
0'
1&
1$
0#
#6050000
10
0"
1!
0*
#6100000
1/
1+
00
#6150000
1-
0/
#6200000
0-
#7000000
0(
1'
1#
#7050000
11
0!
1,
#7100000
12
0+
#7150000
1-
01
#7200000
02
#7250000
0-
